{
  "type": "Program",
  "start": 0,
  "end": 727,
  "loc": {
    "start": {
      "line": 1,
      "column": 0
    },
    "end": {
      "line": 51,
      "column": 1
    }
  },
  "sourceType": "module",
  "body": [
    {
      "type": "ExpressionStatement",
      "start": 0,
      "end": 13,
      "loc": {
        "start": {
          "line": 1,
          "column": 0
        },
        "end": {
          "line": 1,
          "column": 13
        }
      },
      "expression": {
        "type": "Literal",
        "start": 0,
        "end": 12,
        "loc": {
          "start": {
            "line": 1,
            "column": 0
          },
          "end": {
            "line": 1,
            "column": 12
          }
        },
        "value": "use strict",
        "rawValue": "use strict",
        "raw": "'use strict'"
      },
      "trailingComments": [
        {
          "type": "Block",
          "value": "*\n * This class should contain all of our reusable functions\n ",
          "start": 15,
          "end": 81,
          "loc": {
            "start": {
              "line": 3,
              "column": 0
            },
            "end": {
              "line": 5,
              "column": 3
            }
          },
          "range": [
            15,
            81
          ]
        }
      ]
    },
    {
      "type": "ExportDefaultDeclaration",
      "start": 82,
      "end": 727,
      "loc": {
        "start": {
          "line": 6,
          "column": 0
        },
        "end": {
          "line": 51,
          "column": 1
        }
      },
      "declaration": {
        "type": "ClassDeclaration",
        "start": 97,
        "end": 727,
        "loc": {
          "start": {
            "line": 6,
            "column": 15
          },
          "end": {
            "line": 51,
            "column": 1
          }
        },
        "id": {
          "type": "Identifier",
          "start": 103,
          "end": 112,
          "loc": {
            "start": {
              "line": 6,
              "column": 21
            },
            "end": {
              "line": 6,
              "column": 30
            }
          },
          "name": "Functions",
          "leadingComments": null
        },
        "superClass": null,
        "body": {
          "type": "ClassBody",
          "start": 113,
          "end": 727,
          "loc": {
            "start": {
              "line": 6,
              "column": 31
            },
            "end": {
              "line": 51,
              "column": 1
            }
          },
          "body": [
            {
              "type": "MethodDefinition",
              "start": 230,
              "end": 276,
              "loc": {
                "start": {
                  "line": 13,
                  "column": 4
                },
                "end": {
                  "line": 15,
                  "column": 5
                }
              },
              "computed": false,
              "key": {
                "type": "Identifier",
                "start": 237,
                "end": 245,
                "loc": {
                  "start": {
                    "line": 13,
                    "column": 11
                  },
                  "end": {
                    "line": 13,
                    "column": 19
                  }
                },
                "name": "identity"
              },
              "static": true,
              "kind": "method",
              "value": {
                "type": "FunctionExpression",
                "start": 245,
                "end": 276,
                "loc": {
                  "start": {
                    "line": 13,
                    "column": 19
                  },
                  "end": {
                    "line": 15,
                    "column": 5
                  }
                },
                "id": null,
                "generator": false,
                "expression": false,
                "async": false,
                "params": [],
                "body": {
                  "type": "BlockStatement",
                  "start": 248,
                  "end": 276,
                  "loc": {
                    "start": {
                      "line": 13,
                      "column": 22
                    },
                    "end": {
                      "line": 15,
                      "column": 5
                    }
                  },
                  "body": [
                    {
                      "type": "ReturnStatement",
                      "start": 258,
                      "end": 270,
                      "loc": {
                        "start": {
                          "line": 14,
                          "column": 8
                        },
                        "end": {
                          "line": 14,
                          "column": 20
                        }
                      },
                      "argument": {
                        "type": "ThisExpression",
                        "start": 265,
                        "end": 269,
                        "loc": {
                          "start": {
                            "line": 14,
                            "column": 15
                          },
                          "end": {
                            "line": 14,
                            "column": 19
                          }
                        }
                      }
                    }
                  ],
                  "trailingComments": null
                },
                "trailingComments": null
              },
              "leadingComments": [
                {
                  "type": "Block",
                  "value": "*\n     * Returns the current scope that you're calling from.\n     *\n     * @returns {Functions}\n     ",
                  "start": 120,
                  "end": 225,
                  "loc": {
                    "start": {
                      "line": 8,
                      "column": 4
                    },
                    "end": {
                      "line": 12,
                      "column": 7
                    }
                  },
                  "range": [
                    120,
                    225
                  ]
                }
              ],
              "trailingComments": [
                {
                  "type": "Block",
                  "value": "*\n     * Always returns true\n     *\n     * @returns {boolean} true\n     ",
                  "start": 282,
                  "end": 358,
                  "loc": {
                    "start": {
                      "line": 17,
                      "column": 4
                    },
                    "end": {
                      "line": 21,
                      "column": 7
                    }
                  },
                  "range": [
                    282,
                    358
                  ]
                }
              ]
            },
            {
              "type": "MethodDefinition",
              "start": 363,
              "end": 404,
              "loc": {
                "start": {
                  "line": 22,
                  "column": 4
                },
                "end": {
                  "line": 24,
                  "column": 5
                }
              },
              "computed": false,
              "key": {
                "type": "Identifier",
                "start": 370,
                "end": 373,
                "loc": {
                  "start": {
                    "line": 22,
                    "column": 11
                  },
                  "end": {
                    "line": 22,
                    "column": 14
                  }
                },
                "name": "yes"
              },
              "static": true,
              "kind": "method",
              "value": {
                "type": "FunctionExpression",
                "start": 373,
                "end": 404,
                "loc": {
                  "start": {
                    "line": 22,
                    "column": 14
                  },
                  "end": {
                    "line": 24,
                    "column": 5
                  }
                },
                "id": null,
                "generator": false,
                "expression": false,
                "async": false,
                "params": [],
                "body": {
                  "type": "BlockStatement",
                  "start": 376,
                  "end": 404,
                  "loc": {
                    "start": {
                      "line": 22,
                      "column": 17
                    },
                    "end": {
                      "line": 24,
                      "column": 5
                    }
                  },
                  "body": [
                    {
                      "type": "ReturnStatement",
                      "start": 386,
                      "end": 398,
                      "loc": {
                        "start": {
                          "line": 23,
                          "column": 8
                        },
                        "end": {
                          "line": 23,
                          "column": 20
                        }
                      },
                      "argument": {
                        "type": "Literal",
                        "start": 393,
                        "end": 397,
                        "loc": {
                          "start": {
                            "line": 23,
                            "column": 15
                          },
                          "end": {
                            "line": 23,
                            "column": 19
                          }
                        },
                        "value": true,
                        "rawValue": true,
                        "raw": "true"
                      }
                    }
                  ]
                }
              },
              "leadingComments": [
                {
                  "type": "Block",
                  "value": "*\n     * Always returns true\n     *\n     * @returns {boolean} true\n     ",
                  "start": 282,
                  "end": 358,
                  "loc": {
                    "start": {
                      "line": 17,
                      "column": 4
                    },
                    "end": {
                      "line": 21,
                      "column": 7
                    }
                  },
                  "range": [
                    282,
                    358
                  ]
                }
              ]
            },
            {
              "type": "MethodDefinition",
              "start": 410,
              "end": 435,
              "loc": {
                "start": {
                  "line": 26,
                  "column": 4
                },
                "end": {
                  "line": 28,
                  "column": 5
                }
              },
              "computed": false,
              "key": {
                "type": "Identifier",
                "start": 417,
                "end": 424,
                "loc": {
                  "start": {
                    "line": 26,
                    "column": 11
                  },
                  "end": {
                    "line": 26,
                    "column": 18
                  }
                },
                "name": "emptyFn"
              },
              "static": true,
              "kind": "method",
              "value": {
                "type": "FunctionExpression",
                "start": 424,
                "end": 435,
                "loc": {
                  "start": {
                    "line": 26,
                    "column": 18
                  },
                  "end": {
                    "line": 28,
                    "column": 5
                  }
                },
                "id": null,
                "generator": false,
                "expression": false,
                "async": false,
                "params": [],
                "body": {
                  "type": "BlockStatement",
                  "start": 427,
                  "end": 435,
                  "loc": {
                    "start": {
                      "line": 26,
                      "column": 21
                    },
                    "end": {
                      "line": 28,
                      "column": 5
                    }
                  },
                  "body": [],
                  "leadingComments": null,
                  "trailingComments": null
                },
                "trailingComments": null
              },
              "trailingComments": [
                {
                  "type": "Block",
                  "value": "*\n     * Always returns false\n     *\n     * @returns {boolean} false\n     ",
                  "start": 441,
                  "end": 519,
                  "loc": {
                    "start": {
                      "line": 30,
                      "column": 4
                    },
                    "end": {
                      "line": 34,
                      "column": 7
                    }
                  },
                  "range": [
                    441,
                    519
                  ]
                }
              ]
            },
            {
              "type": "MethodDefinition",
              "start": 524,
              "end": 565,
              "loc": {
                "start": {
                  "line": 35,
                  "column": 4
                },
                "end": {
                  "line": 37,
                  "column": 5
                }
              },
              "computed": false,
              "key": {
                "type": "Identifier",
                "start": 531,
                "end": 533,
                "loc": {
                  "start": {
                    "line": 35,
                    "column": 11
                  },
                  "end": {
                    "line": 35,
                    "column": 13
                  }
                },
                "name": "no"
              },
              "static": true,
              "kind": "method",
              "value": {
                "type": "FunctionExpression",
                "start": 533,
                "end": 565,
                "loc": {
                  "start": {
                    "line": 35,
                    "column": 13
                  },
                  "end": {
                    "line": 37,
                    "column": 5
                  }
                },
                "id": null,
                "generator": false,
                "expression": false,
                "async": false,
                "params": [],
                "body": {
                  "type": "BlockStatement",
                  "start": 536,
                  "end": 565,
                  "loc": {
                    "start": {
                      "line": 35,
                      "column": 16
                    },
                    "end": {
                      "line": 37,
                      "column": 5
                    }
                  },
                  "body": [
                    {
                      "type": "ReturnStatement",
                      "start": 546,
                      "end": 559,
                      "loc": {
                        "start": {
                          "line": 36,
                          "column": 8
                        },
                        "end": {
                          "line": 36,
                          "column": 21
                        }
                      },
                      "argument": {
                        "type": "Literal",
                        "start": 553,
                        "end": 558,
                        "loc": {
                          "start": {
                            "line": 36,
                            "column": 15
                          },
                          "end": {
                            "line": 36,
                            "column": 20
                          }
                        },
                        "value": false,
                        "rawValue": false,
                        "raw": "false"
                      }
                    }
                  ]
                }
              },
              "leadingComments": [
                {
                  "type": "Block",
                  "value": "*\n     * Always returns false\n     *\n     * @returns {boolean} false\n     ",
                  "start": 441,
                  "end": 519,
                  "loc": {
                    "start": {
                      "line": 30,
                      "column": 4
                    },
                    "end": {
                      "line": 34,
                      "column": 7
                    }
                  },
                  "range": [
                    441,
                    519
                  ]
                }
              ]
            },
            {
              "type": "MethodDefinition",
              "start": 571,
              "end": 611,
              "loc": {
                "start": {
                  "line": 39,
                  "column": 4
                },
                "end": {
                  "line": 41,
                  "column": 5
                }
              },
              "computed": false,
              "key": {
                "type": "Identifier",
                "start": 578,
                "end": 580,
                "loc": {
                  "start": {
                    "line": 39,
                    "column": 11
                  },
                  "end": {
                    "line": 39,
                    "column": 13
                  }
                },
                "name": "ok"
              },
              "static": true,
              "kind": "method",
              "value": {
                "type": "FunctionExpression",
                "start": 580,
                "end": 611,
                "loc": {
                  "start": {
                    "line": 39,
                    "column": 13
                  },
                  "end": {
                    "line": 41,
                    "column": 5
                  }
                },
                "id": null,
                "generator": false,
                "expression": false,
                "async": false,
                "params": [],
                "body": {
                  "type": "BlockStatement",
                  "start": 583,
                  "end": 611,
                  "loc": {
                    "start": {
                      "line": 39,
                      "column": 16
                    },
                    "end": {
                      "line": 41,
                      "column": 5
                    }
                  },
                  "body": [
                    {
                      "type": "ReturnStatement",
                      "start": 593,
                      "end": 605,
                      "loc": {
                        "start": {
                          "line": 40,
                          "column": 8
                        },
                        "end": {
                          "line": 40,
                          "column": 20
                        }
                      },
                      "argument": {
                        "type": "ThisExpression",
                        "start": 600,
                        "end": 604,
                        "loc": {
                          "start": {
                            "line": 40,
                            "column": 15
                          },
                          "end": {
                            "line": 40,
                            "column": 19
                          }
                        }
                      }
                    }
                  ]
                }
              }
            },
            {
              "type": "MethodDefinition",
              "start": 617,
              "end": 665,
              "loc": {
                "start": {
                  "line": 43,
                  "column": 4
                },
                "end": {
                  "line": 45,
                  "column": 5
                }
              },
              "computed": false,
              "key": {
                "type": "Identifier",
                "start": 624,
                "end": 634,
                "loc": {
                  "start": {
                    "line": 43,
                    "column": 11
                  },
                  "end": {
                    "line": 43,
                    "column": 21
                  }
                },
                "name": "identityFn"
              },
              "static": true,
              "kind": "method",
              "value": {
                "type": "FunctionExpression",
                "start": 634,
                "end": 665,
                "loc": {
                  "start": {
                    "line": 43,
                    "column": 21
                  },
                  "end": {
                    "line": 45,
                    "column": 5
                  }
                },
                "id": null,
                "generator": false,
                "expression": false,
                "async": false,
                "params": [],
                "body": {
                  "type": "BlockStatement",
                  "start": 637,
                  "end": 665,
                  "loc": {
                    "start": {
                      "line": 43,
                      "column": 24
                    },
                    "end": {
                      "line": 45,
                      "column": 5
                    }
                  },
                  "body": [
                    {
                      "type": "ReturnStatement",
                      "start": 647,
                      "end": 659,
                      "loc": {
                        "start": {
                          "line": 44,
                          "column": 8
                        },
                        "end": {
                          "line": 44,
                          "column": 20
                        }
                      },
                      "argument": {
                        "type": "ThisExpression",
                        "start": 654,
                        "end": 658,
                        "loc": {
                          "start": {
                            "line": 44,
                            "column": 15
                          },
                          "end": {
                            "line": 44,
                            "column": 19
                          }
                        }
                      }
                    }
                  ]
                }
              }
            },
            {
              "type": "MethodDefinition",
              "start": 671,
              "end": 724,
              "loc": {
                "start": {
                  "line": 47,
                  "column": 4
                },
                "end": {
                  "line": 49,
                  "column": 5
                }
              },
              "computed": false,
              "key": {
                "type": "Identifier",
                "start": 678,
                "end": 691,
                "loc": {
                  "start": {
                    "line": 47,
                    "column": 11
                  },
                  "end": {
                    "line": 47,
                    "column": 24
                  }
                },
                "name": "passthroughFn"
              },
              "static": true,
              "kind": "method",
              "value": {
                "type": "FunctionExpression",
                "start": 691,
                "end": 724,
                "loc": {
                  "start": {
                    "line": 47,
                    "column": 24
                  },
                  "end": {
                    "line": 49,
                    "column": 5
                  }
                },
                "id": null,
                "generator": false,
                "expression": false,
                "async": false,
                "params": [
                  {
                    "type": "Identifier",
                    "start": 692,
                    "end": 695,
                    "loc": {
                      "start": {
                        "line": 47,
                        "column": 25
                      },
                      "end": {
                        "line": 47,
                        "column": 28
                      }
                    },
                    "name": "arg"
                  }
                ],
                "body": {
                  "type": "BlockStatement",
                  "start": 697,
                  "end": 724,
                  "loc": {
                    "start": {
                      "line": 47,
                      "column": 30
                    },
                    "end": {
                      "line": 49,
                      "column": 5
                    }
                  },
                  "body": [
                    {
                      "type": "ReturnStatement",
                      "start": 707,
                      "end": 718,
                      "loc": {
                        "start": {
                          "line": 48,
                          "column": 8
                        },
                        "end": {
                          "line": 48,
                          "column": 19
                        }
                      },
                      "argument": {
                        "type": "Identifier",
                        "start": 714,
                        "end": 717,
                        "loc": {
                          "start": {
                            "line": 48,
                            "column": 15
                          },
                          "end": {
                            "line": 48,
                            "column": 18
                          }
                        },
                        "name": "arg"
                      }
                    }
                  ]
                }
              }
            }
          ]
        },
        "leadingComments": [
          {
            "type": "Block",
            "value": "*\n * This class should contain all of our reusable functions\n ",
            "start": 15,
            "end": 81,
            "loc": {
              "start": {
                "line": 3,
                "column": 0
              },
              "end": {
                "line": 5,
                "column": 3
              }
            },
            "range": [
              15,
              81
            ]
          }
        ],
        "trailingComments": []
      },
      "leadingComments": [
        {
          "type": "Block",
          "value": "*\n * This class should contain all of our reusable functions\n ",
          "start": 15,
          "end": 81,
          "loc": {
            "start": {
              "line": 3,
              "column": 0
            },
            "end": {
              "line": 5,
              "column": 3
            }
          },
          "range": [
            15,
            81
          ]
        }
      ]
    }
  ]
}